README.txt
setup.cfg
setup.py
dist/teamrubber.pdberrorlog-1.0dev.tar.gz
docs/HISTORY.txt
teamrubber/__init__.py
teamrubber.pdberrorlog.egg-info/PKG-INFO
teamrubber.pdberrorlog.egg-info/SOURCES.txt
teamrubber.pdberrorlog.egg-info/dependency_links.txt
teamrubber.pdberrorlog.egg-info/entry_points.txt
teamrubber.pdberrorlog.egg-info/namespace_packages.txt
teamrubber.pdberrorlog.egg-info/not-zip-safe
teamrubber.pdberrorlog.egg-info/requires.txt
teamrubber.pdberrorlog.egg-info/top_level.txt
teamrubber/pdberrorlog/__init__.py
teamrubber/pdberrorlog/configure.zcml
teamrubber/pdberrorlog/emptylog.html
teamrubber/pdberrorlog/noentries.html
teamrubber/pdberrorlog/tests.py
teamrubber/pdberrorlog/twentyentries.html
teamrubber/pdberrorlog/twoentries.html