Metadata-Version: 1.0
Name: teamrubber.pdberrorlog
Version: 1.1
Summary: Allows a nice interface to the Plone error log from ztc functional tests
Home-page: http://teamrubber.com
Author: Matthew Wilkes
Author-email: matt.wilkes@teamrubber.com
License: GPL
Keywords: plone pdb unittest
Platform: UNKNOWN
Classifier: Programming Language :: Python
Classifier: Topic :: Software Development :: Libraries :: Python Modules
